<annotation>
	<folder>ss1</folder>
	<filename>ss1.png</filename>
	<path>/Users/daggubatisirichandana/PycharmProjects/chart_percept/Chart-Analyzer Scatt/Data/ss1/ss1.png</path>
	<source>
		<database>Unknown</database>
	</source>
	<size>
		<width>752</width>
		<height>676</height>
		<depth>3</depth>
	</size>
	<segmented>0</segmented>
	<object>
		<name>canvas</name>
		<pose>Unspecified</pose>
		<truncated>0</truncated>
		<difficult>0</difficult>
		<bndbox>
			<xmin>208</xmin>
			<ymin>131</ymin>
			<xmax>683</xmax>
			<ymax>545</ymax>
		</bndbox>
	</object>
	<object>
		<name>title</name>
		<pose>Unspecified</pose>
		<truncated>0</truncated>
		<difficult>0</difficult>
		<bndbox>
			<xmin>154</xmin>
			<ymin>21</ymin>
			<xmax>665</xmax>
			<ymax>131</ymax>
		</bndbox>
	</object>
	<object>
		<name>y-title</name>
		<pose>Unspecified</pose>
		<truncated>0</truncated>
		<difficult>0</difficult>
		<bndbox>
			<xmin>12</xmin>
			<ymin>233</ymin>
			<xmax>98</xmax>
			<ymax>442</ymax>
		</bndbox>
	</object>
	<object>
		<name>y-labels</name>
		<pose>Unspecified</pose>
		<truncated>0</truncated>
		<difficult>0</difficult>
		<bndbox>
			<xmin>113</xmin>
			<ymin>133</ymin>
			<xmax>133</xmax>
			<ymax>588</ymax>
		</bndbox>
	</object>
	<object>
		<name>x-title</name>
		<pose>Unspecified</pose>
		<truncated>1</truncated>
		<difficult>0</difficult>
		<bndbox>
			<xmin>162</xmin>
			<ymin>619</ymin>
			<xmax>653</xmax>
			<ymax>676</ymax>
		</bndbox>
	</object>
	<object>
		<name>x-labels</name>
		<pose>Unspecified</pose>
		<truncated>0</truncated>
		<difficult>0</difficult>
		<bndbox>
			<xmin>133</xmin>
			<ymin>583</ymin>
			<xmax>692</xmax>
			<ymax>608</ymax>
		</bndbox>
	</object>
</annotation>
